{
  "id": "cdaa9cb4",
  "name": "gieo-gio-gat-bao",
  "text_path": null,
  "audio_path": null,
  "narrator": {
    "id": "9242944a",
    "name": "Thái Hoàng Phi",
    "dialect": null,
    "gender": null,
    "age": null,
    "url": "https://sachnoiviet.net/giong-doc/thai-hoang-phi",
    "tone": null,
    "volume": null,
    "speed": null,
    "pitch": null
  },
  "duration": 6.3464,
  "author": "Bình Nguyên Lộc",
  "text_url": "https://thuviensachpdf.com/gieo-gio-gat-bao",
  "audio_url": "https://sachnoiviet.net/sach-noi/gieo-gio-gat-bao"
}