{
  "id": "dc77901d",
  "name": "hai-tuong-hat-boi",
  "text_path": null,
  "audio_path": null,
  "narrator": {
    "id": "90aaa551",
    "name": "Thủy Tiên",
    "dialect": null,
    "gender": null,
    "age": null,
    "url": "https://sachnoiviet.net/giong-doc/thuy-tien",
    "tone": null,
    "volume": null,
    "speed": null,
    "pitch": null
  },
  "duration": 3.4211,
  "author": "Vũ Đức Sao Biển",
  "text_url": "https://thuviensachpdf.com/hai-tuong-hat-boi",
  "audio_url": "https://sachnoiviet.net/sach-noi/hai-tuong-hat-boi"
}