{
  "id": "0042004d",
  "name": "lam-giau-voi-su-binh-an-tam-tri",
  "text_path": null,
  "audio_path": null,
  "narrator": {
    "id": "4ecccd01",
    "name": "Việt Dũng",
    "dialect": null,
    "gender": null,
    "age": null,
    "url": "https://sachnoiviet.net/giong-doc/viet-dung",
    "tone": null,
    "volume": null,
    "speed": null,
    "pitch": null
  },
  "duration": 9.7736,
  "author": "Napoleon Hill",
  "text_url": "https://thuviensachpdf.com/lam-giau-voi-su-binh-an-tam-tri",
  "audio_url": "https://sachnoiviet.net/sach-noi/lam-giau-voi-su-binh-an-tam-tri"
}