{
  "id": "fcdab1e5",
  "name": "nhung-cau-chuyen-cua-homer",
  "text_path": null,
  "audio_path": null,
  "narrator": {
    "id": "7aabb08f",
    "name": "Minh Hoàng",
    "dialect": null,
    "gender": null,
    "age": null,
    "url": "https://sachnoiviet.net/giong-doc/minh-hoang",
    "tone": null,
    "volume": null,
    "speed": null,
    "pitch": null
  },
  "duration": 1.975,
  "author": "Cao Xuân Hạo",
  "text_url": "https://thuviensachpdf.com/nhung-cau-chuyen-cua-homer",
  "audio_url": "https://sachnoiviet.net/sach-noi/nhung-cau-chuyen-cua-homer"
}