{
  "id": "0b09125a",
  "name": "tim-ve-suc-manh-vo-bien",
  "text_path": null,
  "audio_path": null,
  "narrator": {
    "id": "d7ffd54e",
    "name": "Phương Anh",
    "dialect": null,
    "gender": null,
    "age": null,
    "url": "https://sachnoiviet.net/giong-doc/phuong-anh",
    "tone": null,
    "volume": null,
    "speed": null,
    "pitch": null
  },
  "duration": 4.2389,
  "author": "Robin Sharma",
  "text_url": "https://thuviensachpdf.com/tim-ve-suc-manh-vo-bien",
  "audio_url": "https://sachnoiviet.net/sach-noi/tim-ve-suc-manh-vo-bien"
}